sourcemapr/__init__.py
sourcemapr/cli.py
sourcemapr/store.py
sourcemapr/tracer.py
sourcemapr/providers/__init__.py
sourcemapr/providers/base.py
sourcemapr/providers/langchain.py
sourcemapr/providers/llamaindex.py
sourcemapr/providers/openai.py
sourcemapr/server/__init__.py
sourcemapr/server/app.py
sourcemapr/server/database.py
sourcemapr/server/static/dist/demo-data.json
sourcemapr/server/static/dist/index.html
sourcemapr/server/static/dist/assets/__vite-browser-external-BIHI7g3E.js
sourcemapr/server/static/dist/assets/charts-6E8qty1X.js
sourcemapr/server/static/dist/assets/index-BwFiYnms.css
sourcemapr/server/static/dist/assets/index-NIvGtT8z.js
sourcemapr/server/static/dist/assets/pdf-BPJ_wLYl.js
sourcemapr/server/static/dist/assets/query-BwGKHU3d.js
sourcemapr/server/static/dist/assets/react-vendor-CuQIHkeY.js
sourcemapr/server/static/js/pdf-viewer.js
sourcemapr/server/templates/index.html
sourcemapr-0.1.1.dist-info/METADATA
sourcemapr-0.1.1.dist-info/WHEEL
sourcemapr-0.1.1.dist-info/entry_points.txt
sourcemapr-0.1.1.dist-info/top_level.txt
sourcemapr-0.1.1.dist-info/RECORD
