Metadata-Version: 2.4
Name: sourcemapr
Version: 0.1.1
Summary: RAG Observability Platform - Trace, debug and understand your RAG pipelines
Author-email: Hrishikesh Kamath <kamathhrishi@gmail.com>
License-Expression: MIT
Project-URL: Homepage, https://github.com/kamathhrishi/sourcemapr
Project-URL: Documentation, https://github.com/kamathhrishi/sourcemapr#readme
Project-URL: Repository, https://github.com/kamathhrishi/sourcemapr
Project-URL: Issues, https://github.com/kamathhrishi/sourcemapr/issues
Keywords: rag,observability,llm,llamaindex,tracing,debugging
Classifier: Development Status :: 4 - Beta
Classifier: Intended Audience :: Developers
Classifier: Programming Language :: Python :: 3
Classifier: Programming Language :: Python :: 3.9
Classifier: Programming Language :: Python :: 3.10
Classifier: Programming Language :: Python :: 3.11
Classifier: Programming Language :: Python :: 3.12
Classifier: Topic :: Software Development :: Libraries :: Python Modules
Classifier: Topic :: Scientific/Engineering :: Artificial Intelligence
Requires-Python: >=3.9
Requires-Dist: requests>=2.28.0
Requires-Dist: fastapi>=0.100.0
Requires-Dist: uvicorn>=0.22.0
Requires-Dist: pydantic>=2.0.0
Provides-Extra: dev
Requires-Dist: pytest>=7.0.0; extra == "dev"
Requires-Dist: pytest-asyncio>=0.21.0; extra == "dev"
Requires-Dist: black>=23.0.0; extra == "dev"
Requires-Dist: ruff>=0.1.0; extra == "dev"
Provides-Extra: llamaindex
Requires-Dist: llama-index>=0.10.0; extra == "llamaindex"
Requires-Dist: llama-index-embeddings-huggingface>=0.2.0; extra == "llamaindex"
Provides-Extra: sec
Requires-Dist: llama-index>=0.10.0; extra == "sec"
Requires-Dist: llama-index-readers-file>=0.1.0; extra == "sec"
Requires-Dist: llama-index-embeddings-huggingface>=0.2.0; extra == "sec"
Requires-Dist: unstructured>=0.10.0; extra == "sec"
